README.md
setup.py
libpythonpro/__init__.py
libpythonpro/github_api.py
raol_libpyhtonpro.egg-info/PKG-INFO
raol_libpyhtonpro.egg-info/SOURCES.txt
raol_libpyhtonpro.egg-info/dependency_links.txt
raol_libpyhtonpro.egg-info/not-zip-safe
raol_libpyhtonpro.egg-info/requires.txt
raol_libpyhtonpro.egg-info/top_level.txt